BianxieRubyDeCTuozhan/README.md
BianxieRubyDeCTuozhan/__init__.py
BianxieRubyDeCTuozhan/__main__.py
BianxieRubyDeCTuozhan/file.epub
BianxieRubyDeCTuozhan/index.html
BianxieRubyDeCTuozhan/css/__init__.py
BianxieRubyDeCTuozhan/css/annotations.css
BianxieRubyDeCTuozhan/css/main.css
BianxieRubyDeCTuozhan/css/normalize.css
BianxieRubyDeCTuozhan/css/popup.css
BianxieRubyDeCTuozhan/font/__init__.py
BianxieRubyDeCTuozhan/font/fontello.eot
BianxieRubyDeCTuozhan/font/fontello.svg
BianxieRubyDeCTuozhan/font/fontello.ttf
BianxieRubyDeCTuozhan/font/fontello.woff
BianxieRubyDeCTuozhan/img/__init__.py
BianxieRubyDeCTuozhan/img/annotator-glyph-sprite.png
BianxieRubyDeCTuozhan/img/annotator-icon-sprite.png
BianxieRubyDeCTuozhan/img/apple-touch-icon.png
BianxieRubyDeCTuozhan/img/cancelfullscreen.png
BianxieRubyDeCTuozhan/img/close.png
BianxieRubyDeCTuozhan/img/fullscreen.png
BianxieRubyDeCTuozhan/img/loader.gif
BianxieRubyDeCTuozhan/img/menu-icon.png
BianxieRubyDeCTuozhan/img/save.png
BianxieRubyDeCTuozhan/img/saved.png
BianxieRubyDeCTuozhan/img/settings-s.png
BianxieRubyDeCTuozhan/img/settings.png
BianxieRubyDeCTuozhan/img/star.png
BianxieRubyDeCTuozhan/js/__init__.py
BianxieRubyDeCTuozhan/js/epub.js
BianxieRubyDeCTuozhan/js/epub.min.js
BianxieRubyDeCTuozhan/js/epub.min.map
BianxieRubyDeCTuozhan/js/hooks.min.js
BianxieRubyDeCTuozhan/js/hooks.min.map
BianxieRubyDeCTuozhan/js/reader.js
BianxieRubyDeCTuozhan/js/reader.js.map
BianxieRubyDeCTuozhan/js/reader.min.js
BianxieRubyDeCTuozhan/js/reader.min.map
BianxieRubyDeCTuozhan/js/hooks/__init__.py
BianxieRubyDeCTuozhan/js/hooks/extensions/__init__.py
BianxieRubyDeCTuozhan/js/hooks/extensions/highlight.js
BianxieRubyDeCTuozhan/js/libs/__init__.py
BianxieRubyDeCTuozhan/js/libs/jquery.min.js
BianxieRubyDeCTuozhan/js/libs/localforage.min.js
BianxieRubyDeCTuozhan/js/libs/screenfull.js
BianxieRubyDeCTuozhan/js/libs/screenfull.min.js
BianxieRubyDeCTuozhan/js/libs/zip.min.js
BianxieRubyDeCTuozhan/js/plugins/__init__.py
bianxie_ruby_de_c_tuozhan-2024.3.1.0.dist-info/METADATA
bianxie_ruby_de_c_tuozhan-2024.3.1.0.dist-info/WHEEL
bianxie_ruby_de_c_tuozhan-2024.3.1.0.dist-info/entry_points.txt
bianxie_ruby_de_c_tuozhan-2024.3.1.0.dist-info/top_level.txt
bianxie_ruby_de_c_tuozhan-2024.3.1.0.dist-info/RECORD
